eml_analyzer/__init__.py
eml_analyzer/cli_script.py
eml_parse-2.0.0.dist-info/LICENSE
eml_parse-2.0.0.dist-info/METADATA
eml_parse-2.0.0.dist-info/WHEEL
eml_parse-2.0.0.dist-info/entry_points.txt
eml_parse-2.0.0.dist-info/top_level.txt
eml_parse-2.0.0.dist-info/RECORD
