Metadata-Version: 2.1
Name: eml-parse
Version: 2.0.0
Summary: A cli script to analyze an E-Mail in the eml format for viewing the header, extracting attachments etc.
Home-page: https://github.com/debragail/eml_analyzer
Author: Debra White
Author-email: git@27c1ub.com
License: UNKNOWN
Platform: UNKNOWN
Classifier: Programming Language :: Python :: 3
Classifier: License :: OSI Approved :: MIT License
Classifier: Operating System :: OS Independent
Requires-Dist: cli-formatter (>=1.2.0)
